duckbot_matrix/__init__.py
duckbot_matrix/__main__.py
duckbot_matrix/command_processor.py
duckbot_matrix/command_response.py
duckbot_matrix/config.py
duckbot_matrix/duckbot.py
duckbot_matrix/matrix_client.py
duckbot_matrix/matrix_client_pg_storage.py
duckbot_matrix/test.py
duckbot_matrix/translation_module.py
duckbot_matrix-0.2.4.dist-info/LICENSE
duckbot_matrix-0.2.4.dist-info/METADATA
duckbot_matrix-0.2.4.dist-info/WHEEL
duckbot_matrix-0.2.4.dist-info/top_level.txt
duckbot_matrix-0.2.4.dist-info/RECORD
