Metadata-Version: 2.1
Name: duckbot-matrix
Version: 0.2.4
Summary: A simple Matrix bot.
Author-email: Hannes Nisula <hannes@ducksquad.dev>
License: MIT
Requires-Python: >=3.10
License-File: LICENSE
Requires-Dist: asyncio
Requires-Dist: psycopg2
Requires-Dist: uuid
Requires-Dist: aiohttp
Requires-Dist: deepl
Requires-Dist: pyyaml
